<ui:UiBinder xmlns:ui="urn:ui:com.google.gwt.uibinder"
             xmlns:g="urn:import:com.google.gwt.user.client.ui"
             xmlns:w="urn:import:org.openremote.manager.client.widget">

    <ui:with field="constants" type="org.openremote.manager.client.i18n.ManagerConstants"/>
    <ui:with field="widgetStyle" type="org.openremote.manager.client.style.WidgetStyle"/>
    <ui:with field="themeStyle" type="org.openremote.manager.client.style.ThemeStyle"/>

    <g:HTMLPanel styleName="flex layout vertical">

        <div class="layout horizontal {widgetStyle.FormMessages} {themeStyle.FormMessages}"
             style="max-width: 50%;"
             ui:field="formMessages"/>

        <div class="{widgetStyle.Headline1} {themeStyle.Headline1}">
            <g:InlineLabel text="{constants.editTenant}"/>
        </div>

        <div class="{widgetStyle.HeadlineSub} {themeStyle.HeadlineSub}">
            <span class="required">*</span>
            <g:InlineLabel text="{constants.requiredFields}"/>
        </div>

        <div class="layout vertical {widgetStyle.Form} {themeStyle.Form}" ui:field="form">

            <g:SimplePanel ui:field="cellTableContainer"/>

            <div class="layout horizontal center {widgetStyle.FormGroup} {themeStyle.FormGroup}"
                 ui:field="displayNameGrou">
                <div class="larger {widgetStyle.FormLabel} {themeStyle.FormLabel}">
                    <label ui:field="displayNameLabel">
                        <g:InlineLabel text="{constants.tenantDisplayName}"/>
                    </label>
                    <span class="required">*</span>
                </div>
                <div class="{widgetStyle.FormField} {themeStyle.FormField}">
                    <g:TextBox ui:field="displayNameInput"
                               addStyleNames="{widgetStyle.FormControl} {themeStyle.FormControl} {widgetStyle.FormInputText} {themeStyle.FormInputText}"/>
                </div>
            </div>

            <div class="layout horizontal center {widgetStyle.FormGroup} {themeStyle.FormGroup}"
                 ui:field="realmGroup">
                <div class="larger {widgetStyle.FormLabel} {themeStyle.FormLabel}">
                    <label ui:field="realmLabel">
                        <g:InlineLabel text="{constants.realm}"/>
                    </label>
                    <span class="required">*</span>
                </div>
                <div class="{widgetStyle.FormField} {themeStyle.FormField}">
                    <g:TextBox ui:field="realmInput"
                               addStyleNames="{widgetStyle.FormControl} {themeStyle.FormControl} {widgetStyle.FormInputText} {themeStyle.FormInputText}"/>
                </div>
            </div>

            <div class="layout horizontal center {widgetStyle.FormGroup} {themeStyle.FormGroup}">
                <div class="larger {widgetStyle.FormLabel} {themeStyle.FormLabel}">
                    <label ui:field="enabledLabel">
                        <g:InlineLabel text="{constants.enabled}"/>
                    </label>
                </div>
                <div class="{widgetStyle.FormField} {themeStyle.FormField}">
                    <g:SimpleCheckBox ui:field="enabledCheckBox"
                                      addStyleNames="{widgetStyle.FormControl} {themeStyle.FormControl} {widgetStyle.FormCheckBox} {themeStyle.FormCheckBox}"/>
                </div>
            </div>

            <div class="layout horizontal center {widgetStyle.FormGroup} {themeStyle.FormGroup}">
                <div class="{widgetStyle.FormField} {themeStyle.FormField}">
                    <w:PushButton ui:field="updateButton"
                                  addStyleNames="{widgetStyle.FormControl} {themeStyle.FormControl} {widgetStyle.FormButtonPrimary} {themeStyle.FormButtonPrimary} {widgetStyle.PushButton} {themeStyle.PushButton}"
                                  text="{constants.updateTenant}"
                                  visible="false"
                                  icon="save"/>
                    <w:PushButton ui:field="createButton"
                                  addStyleNames="{widgetStyle.FormControl} {themeStyle.FormControl} {widgetStyle.FormButtonPrimary} {themeStyle.FormButtonPrimary} {widgetStyle.PushButton} {themeStyle.PushButton}"
                                  text="{constants.createTenant}"
                                  visible="false"
                                  icon="save"/>
                    <w:PushButton ui:field="deleteButton"
                                  addStyleNames="{widgetStyle.FormControl} {themeStyle.FormControl} {widgetStyle.FormButtonDanger} {themeStyle.FormButtonDanger} {widgetStyle.PushButton} {themeStyle.PushButton}"
                                  text="{constants.deleteTenant}"
                                  visible="false"
                                  icon="trash"/>
                    <w:PushButton ui:field="cancelButton"
                                  addStyleNames="{widgetStyle.FormControl} {themeStyle.FormControl} {widgetStyle.FormButton} {themeStyle.FormButton} {widgetStyle.PushButton} {themeStyle.PushButton}"
                                  text="{constants.cancel}"
                                  icon="close"/>
                </div>
            </div>

        </div>
    </g:HTMLPanel>

</ui:UiBinder>